{
    "Owner Information": {
        "Name": "John Doe",
        "Address": "123 Maple Street",
        "City, Zip, Address": "Portland, OR 97203",
        "Phone Number": "(503) 555-1234"
    },
    "data": [
        {
            "Number": "1",
            "Area": "",
            "Item Description": "Living Room  Desk",
            "Source": "Target",
            "Purchase Date": "2018-06-07",
            "Style": "Premium",
            "Serial Number": "6DDZ7S36",
            "Value": "$ 846.59",
            "Condition": "Excellent"
        },
        {
            "Number": "2",
            "Area": "Kitchen",
            "Item Description": "LED TV",
            "Source": "Walmart",
            "Purchase Date": "2015-05-31",
            "Style": "Classic",
            "Serial Number": "NJEZ3OPO",
            "Value": "$ 382.04",
            "Condition": "Excellent"
        },
        {
            "Number": "3",
            "Area": "",
            "Item Description": "Living Room LED TV",
            "Source": "Target",
            "Purchase Date": "2019-03-03",
            "Style": "Premium",
            "Serial Number": "HRIS4LI8",
            "Value": "$ 1,603.37",
            "Condition": "Excellent"
        },
        {
            "Number": "4",
            "Area": "Garage",
            "Item Description": "Dining Table",
            "Source": "Wayfair",
            "Purchase Date": "2023-03-26",
            "Style": "Modern",
            "Serial Number": "2HLNMD64",
            "Value": "$ 552.74",
            "Condition": "New"
        },
        {
            "Number": "5",
            "Area": "",
            "Item Description": "Living Room Tool Set",
            "Source": "Target",
            "Purchase Date": "2020-01-06",
            "Style": "Classic",
            "Serial Number": "R08QDU0S",
            "Value": "$ 1,546.39",
            "Condition": "Like New"
        },
        {
            "Number": "6",
            "Area": "Office",
            "Item Description": "LED TV",
            "Source": "Amazon",
            "Purchase Date": "2015-04-03",
            "Style": "Classic",
            "Serial Number": "GSABG41R",
            "Value": "$ 1,319.36",
            "Condition": "Like New"
        },
        {
            "Number": "7",
            "Area": "Office",
            "Item Description": "Mattress",
            "Source": "Amazon",
            "Purchase Date": "2022-02-28",
            "Style": "Premium",
            "Serial Number": "DVTMS64O",
            "Value": "$ 573.10",
            "Condition": "Excellent"
        },
        {
            "Number": "8",
            "Area": "Bedroom",
            "Item Description": "Tool Set   Home Depot",
            "Source": "",
            "Purchase Date": "2017-04-07",
            "Style": "Classic",
            "Serial Number": "RB93WPTH",
            "Value": "$ 1,421.38",
            "Condition": "Excellent"
        },
        {
            "Number": "9",
            "Area": "",
            "Item Description": "Dining Room  Mattress",
            "Source": "Target",
            "Purchase Date": "2017-03-20",
            "Style": "Compact",
            "Serial Number": "7RX8YNW9",
            "Value": "$ 1,760.11",
            "Condition": "Like New"
        },
        {
            "Number": "10",
            "Area": "",
            "Item Description": "Living Room  Desk",
            "Source": "Target",
            "Purchase Date": "2019-06-30",
            "Style": "Classic",
            "Serial Number": "US1B0BQI",
            "Value": "$ 941.43",
            "Condition": "Like New"
        },
        {
            "Number": "11",
            "Area": "Garage",
            "Item Description": "Dining Table",
            "Source": "Wayfair",
            "Purchase Date": "2016-02-09",
            "Style": "Compact",
            "Serial Number": "1J7088BO",
            "Value": "$ 71.12",
            "Condition": "Excellent"
        },
        {
            "Number": "12",
            "Area": "Bedroom",
            "Item Description": "Desk       Home Depot",
            "Source": "",
            "Purchase Date": "2025-08-21",
            "Style": "Modern",
            "Serial Number": "GVJFQYT1",
            "Value": "$ 841.41",
            "Condition": "Like New"
        },
        {
            "Number": "13",
            "Area": "Office",
            "Item Description": "Dining Table Best Buy",
            "Source": "",
            "Purchase Date": "2022-09-23",
            "Style": "Modern",
            "Serial Number": "5EXQQOB1",
            "Value": "$ 1,686.96",
            "Condition": "Excellent"
        },
        {
            "Number": "14",
            "Area": "Kitchen",
            "Item Description": "Dining Table",
            "Source": "Amazon",
            "Purchase Date": "2017-04-07",
            "Style": "Premium",
            "Serial Number": "QZY31U1R",
            "Value": "$ 1,457.39",
            "Condition": "Good"
        },
        {
            "Number": "15",
            "Area": "Garage",
            "Item Description": "Mattress   Home Depot",
            "Source": "",
            "Purchase Date": "2024-05-28",
            "Style": "Classic",
            "Serial Number": "D4FYUJ8E",
            "Value": "$ 182.96",
            "Condition": "New"
        },
        {
            "Number": "16",
            "Area": "Garage",
            "Item Description": "Dining Table",
            "Source": "Amazon",
            "Purchase Date": "2023-08-13",
            "Style": "Premium",
            "Serial Number": "KO6MGEIY",
            "Value": "$ 127.00",
            "Condition": "Excellent"
        },
        {
            "Number": "17",
            "Area": "Kitchen",
            "Item Description": "Tool Set",
            "Source": "Amazon",
            "Purchase Date": "2022-07-12",
            "Style": "Premium",
            "Serial Number": "X7QIEB5T",
            "Value": "$ 1,457.28",
            "Condition": "Excellent"
        },
        {
            "Number": "18",
            "Area": "Garage",
            "Item Description": "Desk",
            "Source": "Walmart",
            "Purchase Date": "2024-08-27",
            "Style": "Compact",
            "Serial Number": "BI1UXOJ9",
            "Value": "$ 103.48",
            "Condition": "New"
        },
        {
            "Number": "19",
            "Area": "Garage",
            "Item Description": "Dining Table",
            "Source": "Amazon",
            "Purchase Date": "2023-10-13",
            "Style": "Classic",
            "Serial Number": "4GEV5RRW",
            "Value": "$ 403.55",
            "Condition": "Like New"
        },
        {
            "Number": "20",
            "Area": "Office",
            "Item Description": "LED TV     Best Buy",
            "Source": "",
            "Purchase Date": "2015-12-12",
            "Style": "Classic",
            "Serial Number": "F7IKU0DS",
            "Value": "$ 541.69",
            "Condition": "Excellent"
        },
        {
            "Number": "21",
            "Area": "",
            "Item Description": "Living Room LED TV",
            "Source": "Amazon",
            "Purchase Date": "2017-07-22",
            "Style": "Premium",
            "Serial Number": "8HCSY97G",
            "Value": "$ 1,851.93",
            "Condition": "Good"
        },
        {
            "Number": "23",
            "Area": "",
            "Item Description": "Living Room Stand Mixer Best Buy",
            "Source": "",
            "Purchase Date": "2017-07-25",
            "Style": "Premium",
            "Serial Number": "3BTI1E79",
            "Value": "$ 1,734.69",
            "Condition": "Excellent"
        },
        {
            "Number": "24",
            "Area": "",
            "Item Description": "Living Room Tool Set",
            "Source": "Amazon",
            "Purchase Date": "2016-03-08",
            "Style": "Classic",
            "Serial Number": "7RBCLH8X",
            "Value": "$ 1,351.20",
            "Condition": "Good"
        },
        {
            "Number": "25",
            "Area": "Bedroom",
            "Item Description": "Dining Table Home Depot",
            "Source": "",
            "Purchase Date": "2020-03-03",
            "Style": "Premium",
            "Serial Number": "W5I85PVW",
            "Value": "$ 148.41",
            "Condition": "Excellent"
        },
        {
            "Number": "26",
            "Area": "",
            "Item Description": "Dining Room  Desk",
            "Source": "Wayfair",
            "Purchase Date": "2021-11-25",
            "Style": "Premium",
            "Serial Number": "YJHBPF1G",
            "Value": "$ 1,896.32",
            "Condition": "Excellent"
        },
        {
            "Number": "27",
            "Area": "",
            "Item Description": "Living Room Dining Table Best Buy",
            "Source": "",
            "Purchase Date": "2020-05-16",
            "Style": "Modern",
            "Serial Number": "GQPBD9OJ",
            "Value": "$ 974.74",
            "Condition": "New"
        },
        {
            "Number": "29",
            "Area": "Garage",
            "Item Description": "Desk",
            "Source": "Walmart",
            "Purchase Date": "2025-09-10",
            "Style": "Modern",
            "Serial Number": "14TNDRC5",
            "Value": "$ 859.33",
            "Condition": "New"
        },
        {
            "Number": "30",
            "Area": "",
            "Item Description": "Dining Room LED TV     Best Buy",
            "Source": "",
            "Purchase Date": "2018-09-15",
            "Style": "Modern",
            "Serial Number": "QDD9Q659",
            "Value": "$ 1,072.67",
            "Condition": "Excellent"
        },
        {
            "Number": "31",
            "Area": "Bedroom",
            "Item Description": "LED TV",
            "Source": "Amazon",
            "Purchase Date": "2024-11-05",
            "Style": "Compact",
            "Serial Number": "DXW026Z7",
            "Value": "$ 129.39",
            "Condition": "Like New"
        },
        {
            "Number": "32",
            "Area": "Kitchen",
            "Item Description": "Tool Set   Best Buy",
            "Source": "",
            "Purchase Date": "2019-11-15",
            "Style": "Compact",
            "Serial Number": "GZFM295X",
            "Value": "$ 1,801.21",
            "Condition": "Like New"
        },
        {
            "Number": "33",
            "Area": "",
            "Item Description": "Dining Room Dining Table",
            "Source": "Amazon",
            "Purchase Date": "2025-02-15",
            "Style": "Classic",
            "Serial Number": "20SQB8Q2",
            "Value": "$ 284.67",
            "Condition": "New"
        }
    ]
}